{
  "name": "hjm-blog Codespace",
  "image": "mcr.microsoft.com/devcontainers/python:3.11",
  "features": {
    "ghcr.io/devcontainers/features/git:1": {},
    "ghcr.io/devcontainers/features/github-cli:1": {}
  },
  "customizations": {
    "vscode": {
      "extensions": [
        "ms-python.python",
        "ms-python.vscode-pylance",
        "streetsidesoftware.code-spell-checker",
        "yzhang.markdown-all-in-one",
        "shd101wyy.markdown-preview-enhanced"
      ],
      "settings": {
        "python.defaultInterpreterPath": "/usr/bin/python3",
        "editor.formatOnSave": true,
        "editor.defaultFormatter": "esbenp.prettier-vscode"
      }
    }
  },
  "postCreateCommand": "pip3 config set global.index-url https://pypi.tuna.tsinghua.edu.cn/simple && pip3 install -r requirements.txt",
  "forwardPorts": [8000],
  "remoteUser": "vscode"
}
